moznetwork/__init__.py
moznetwork/moznetwork.py
moznetwork-1.0.0.dist-info/METADATA
moznetwork-1.0.0.dist-info/WHEEL
moznetwork-1.0.0.dist-info/entry_points.txt
moznetwork-1.0.0.dist-info/top_level.txt
moznetwork-1.0.0.dist-info/RECORD
